liotel/__init__.py
liotel/liotelbot.py
liotel-0.2b1.dist-info/METADATA
liotel-0.2b1.dist-info/WHEEL
liotel-0.2b1.dist-info/entry_points.txt
liotel-0.2b1.dist-info/top_level.txt
liotel-0.2b1.dist-info/RECORD
